WeiboBot/__init__.py
WeiboBot/bot/__init__.py
WeiboBot/bot/bot.py
WeiboBot/bot/event.py
WeiboBot/const/__init__.py
WeiboBot/data/__init__.py
WeiboBot/data/db.py
WeiboBot/data/record.py
WeiboBot/exception/__init__.py
WeiboBot/model/__init__.py
WeiboBot/model/base.py
WeiboBot/model/comment/__init__.py
WeiboBot/model/message/__init__.py
WeiboBot/model/message/chat.py
WeiboBot/model/user/__init__.py
WeiboBot/model/weibo/__init__.py
WeiboBot/model/weibo/page.py
WeiboBot/model/weibo/weibo.py
WeiboBot/net/__init__.py
WeiboBot/net/net_tool.py
WeiboBot/typing/__init__.py
WeiboBot/util/__init__.py
WeiboBot/util/tools.py
weibobot-1.2.3.dist-info/licenses/LICENSE
weibobot-1.2.3.dist-info/METADATA
weibobot-1.2.3.dist-info/WHEEL
weibobot-1.2.3.dist-info/top_level.txt
weibobot-1.2.3.dist-info/RECORD
