Metadata-Version: 2.4
Name: WeiboBot
Version: 1.2.3
Summary: 基于微博H5 API开发的机器人框架
Author-email: Merlin <merlin@merlinblog.cn>
Project-URL: Homepage, https://github.com/MerlinCN/WeiboBot
Keywords: weibo,bot,weibo-bot,weibo-api,weibo-sdk
Classifier: License :: OSI Approved :: GNU Affero General Public License v3
Classifier: Operating System :: OS Independent
Classifier: Programming Language :: Python :: 3.11
Requires-Python: >=3.11
License-File: LICENSE
Requires-Dist: httpx>=0.28.1
Requires-Dist: pytest>=7.0.0
Requires-Dist: pytest-cov>=4.0.0
Requires-Dist: pydantic>=2.11.5
Requires-Dist: tortoise-orm>=0.25.1
Requires-Dist: aiosqlite>=0.21.0
Requires-Dist: qrcode>=8.2
Requires-Dist: loguru>=0.7.3
Requires-Dist: pyqrcode>=1.2.1
Requires-Dist: pillow>=11.2.1
Requires-Dist: socksio>=1.0.0
Requires-Dist: bs4>=0.0.2
Provides-Extra: screenshot
Requires-Dist: playwright>=1.52.0; extra == "screenshot"
Dynamic: license-file
